.gitignore
LICENSE
MANIFEST.in
README.md
__init__.py
install.sh
setup.py
Nproxypool.egg-info/PKG-INFO
Nproxypool.egg-info/SOURCES.txt
Nproxypool.egg-info/dependency_links.txt
Nproxypool.egg-info/entry_points.txt
Nproxypool.egg-info/not-zip-safe
Nproxypool.egg-info/requires.txt
Nproxypool.egg-info/top_level.txt
nproxypool/__init__.py
nproxypool/cmdline.py
nproxypool/base/__init__.py
nproxypool/base/db.py
nproxypool/base/logger.py
nproxypool/base/proxy_fetcher.py
nproxypool/base/server.py
nproxypool/base/synchronizer.py
nproxypool/base/verifier.py
nproxypool/templates/__init__.py
nproxypool/templates/pool/__init__.py
nproxypool/templates/pool/my_fetcher.py
nproxypool/utils/__init__.py
nproxypool/utils/exceptions.py
nproxypool/utils/misc.py
nproxypool/utils/run.py